odoo/addons/base_rest/README.rst
odoo/addons/base_rest/__init__.py
odoo/addons/base_rest/__manifest__.py
odoo/addons/base_rest/core.py
odoo/addons/base_rest/http.py
odoo/addons/base_rest/restapi.py
odoo/addons/base_rest/tools.py
odoo/addons/base_rest/apispec/__init__.py
odoo/addons/base_rest/apispec/base_rest_service_apispec.py
odoo/addons/base_rest/apispec/rest_method_param_plugin.py
odoo/addons/base_rest/apispec/restapi_method_route_plugin.py
odoo/addons/base_rest/components/__init__.py
odoo/addons/base_rest/components/cerberus_validator.py
odoo/addons/base_rest/components/service.py
odoo/addons/base_rest/controllers/__init__.py
odoo/addons/base_rest/controllers/api_docs.py
odoo/addons/base_rest/controllers/main.py
odoo/addons/base_rest/i18n/base_rest.pot
odoo/addons/base_rest/i18n/es.po
odoo/addons/base_rest/models/__init__.py
odoo/addons/base_rest/models/rest_service_registration.py
odoo/addons/base_rest/readme/CONFIGURE.rst
odoo/addons/base_rest/readme/CONTRIBUTORS.rst
odoo/addons/base_rest/readme/DESCRIPTION.rst
odoo/addons/base_rest/readme/HISTORY.rst
odoo/addons/base_rest/readme/ROADMAP.rst
odoo/addons/base_rest/readme/USAGE.rst
odoo/addons/base_rest/static/description/icon.png
odoo/addons/base_rest/static/description/icon.svg
odoo/addons/base_rest/static/description/index.html
odoo/addons/base_rest/static/lib/swagger-ui-3.17.0/favicon-16x16.png
odoo/addons/base_rest/static/lib/swagger-ui-3.17.0/favicon-32x32.png
odoo/addons/base_rest/static/lib/swagger-ui-3.17.0/index.html
odoo/addons/base_rest/static/lib/swagger-ui-3.17.0/oauth2-redirect.html
odoo/addons/base_rest/static/lib/swagger-ui-3.17.0/swagger-ui-bundle.js
odoo/addons/base_rest/static/lib/swagger-ui-3.17.0/swagger-ui-bundle.js.map
odoo/addons/base_rest/static/lib/swagger-ui-3.17.0/swagger-ui-standalone-preset.js
odoo/addons/base_rest/static/lib/swagger-ui-3.17.0/swagger-ui-standalone-preset.js.map
odoo/addons/base_rest/static/lib/swagger-ui-3.17.0/swagger-ui.css
odoo13_addon_base_rest-13.0.3.1.4.dist-info/METADATA
odoo13_addon_base_rest-13.0.3.1.4.dist-info/WHEEL
odoo13_addon_base_rest-13.0.3.1.4.dist-info/top_level.txt
odoo13_addon_base_rest-13.0.3.1.4.dist-info/RECORD
